dicomcrop/__init__.py
dicomcrop/__version__.py
dicomcrop/cli.py
dicomcrop/lib.py
dicomcrop-0.6.dist-info/METADATA
dicomcrop-0.6.dist-info/WHEEL
dicomcrop-0.6.dist-info/entry_points.txt
dicomcrop-0.6.dist-info/top_level.txt
dicomcrop-0.6.dist-info/RECORD
