Metadata-Version: 2.1
Name: dicomcrop
Version: 0.6
Summary: Prepare bedside medical images for machine learning and image interpretation.
Home-page: https://github.com/falcucci/dicomcrop
Author: Alexsander Falcucci
Author-email: alex.falcucci@gmail.com
License: Apache Software License 2.0
Keywords: dicom bedside pocus ffmpeg opencv echo cardiac cancer hospital
Classifier: Intended Audience :: Healthcare Industry
Classifier: Topic :: Scientific/Engineering :: Medical Science Apps.
Classifier: Programming Language :: Python :: 3.7
Classifier: Programming Language :: Python :: 3.8
Requires-Python: >=3.6
Requires-Dist: cffi
Requires-Dist: cryptography
Requires-Dist: dicom2jpg
Requires-Dist: et-xmlfile
Requires-Dist: fire
Requires-Dist: numpy
Requires-Dist: opencv-python
Requires-Dist: openpyxl
Requires-Dist: Pillow
Requires-Dist: pycparser
Requires-Dist: pydicom
Requires-Dist: PyJWT
Requires-Dist: pylibjpeg
Requires-Dist: pylibjpeg-libjpeg
Requires-Dist: pylibjpeg-openjpeg
Requires-Dist: six
Requires-Dist: termcolor
